coda/__init__.py
coda/parser.py
coda/statement.py
coda/tests/Coda_faulty_version.txt
coda/tests/Coda_foreign_account.txt
coda/tests/Coda_v2_3_faulty_globalisation.txt
coda/tests/Coda_v2_3_faulty_globalisation_2.txt
coda/tests/Coda_v2_3_globalisation.txt
coda/tests/Coda_v2_3_globalisation_2.txt
coda/tests/Coda_v2_3_multi_statements.txt
coda/tests/Coda_v2_3_single_statement.txt
coda/tests/__init__.py
coda/tests/test_parser.py
pycoda-1.1.0.dist-info/LICENSE
pycoda-1.1.0.dist-info/METADATA
pycoda-1.1.0.dist-info/WHEEL
pycoda-1.1.0.dist-info/top_level.txt
pycoda-1.1.0.dist-info/RECORD
