Metadata-Version: 2.1
Name: pycoda
Version: 1.1.0
Summary: Python library for Coded statement of account (CODA) 
Home-page: http://pypi.python.org/pypi/pycoda
Author: ACSONE SA/NV
Author-email: laurent.mignon@acsone.eu
License: UNKNOWN
Platform: UNKNOWN
Classifier: Development Status :: 5 - Production/Stable
Classifier: Intended Audience :: Developers
Classifier: Intended Audience :: Financial and Insurance Industry
Classifier: Intended Audience :: Information Technology
Classifier: License :: OSI Approved :: GNU General Public License v3 or later (GPLv3+)
Classifier: Topic :: Software Development :: Libraries :: Python Modules
Classifier: Topic :: Text Processing
Classifier: Topic :: Text Processing :: Markup
Classifier: Programming Language :: Python :: 2
Classifier: Programming Language :: Python :: 3.5
